{
    "version": "0.0.0",
    "networks": {
        "1337": {
            "contracts": {
                "WegaERC20Escrow": {
                    "address": "0x5FC8d32690cc91D4c39d9d3abcBD16989F875707",
                    "legacyAddresses": [
                        "0x5FC8d32690cc91D4c39d9d3abcBD16989F875707"
                    ],
                    "deploymentBlock": "0x06",
                    "implementation": "0xDc64a140Aa3E981100a9becA4E685f962f0cF6C9"
                },
                "WegaERC20Dummy": {
                    "address": "0x5FbDB2315678afecb367f032d93F642f64180aa3",
                    "legacyAddresses": [],
                    "deploymentBlock": "0x01"
                },
                "WegaGameController": {
                    "address": "0x99bbA657f2BbC93c02D617f8bA121cB8Fc104Acf",
                    "legacyAddresses": [
                        "0x5FC8d32690cc91D4c39d9d3abcBD16989F875707"
                    ],
                    "deploymentBlock": "0x2b",
                    "implementation": "0x4826533B4897376654Bb4d4AD88B7faFD0C98528"
                },
                "WegaRandomNumberController": {
                    "address": "0x2279B7A0a67DB372996a5FaB50D91eAA73d2eBe6",
                    "legacyAddresses": [],
                    "deploymentBlock": "0x09",
                    "implementation": "0xa513E6E4b8f2a923D98304ec87F64353C4D5C853"
                },
                "WegaDiceGame": {
                    "address": "0x0DCd1Bf9A1b36cE34237eEaFef220932846BCD82",
                    "legacyAddresses": [],
                    "deploymentBlock": "0x0e",
                    "implementation": "0xA51c1fc2f0D1a1b8494Ed1FE312d7C3a78Ed91C0"
                },
                "WegaCoinFlipGame": {
                    "address": "0xB7f8BC63BbcaD18155201308C8f3540b07f84F5e",
                    "legacyAddresses": [],
                    "deploymentBlock": "0x0c",
                    "implementation": "0x610178dA211FEF7D417bC0e6FeD39F05609AD788"
                },
                "FeeManager": {
                    "address": "0x9fE46736679d2D9a65F0992F2272dE9f3c7fa6e0",
                    "legacyAddresses": [],
                    "deploymentBlock": "0x03",
                    "implementation": "0xe7f1725E7734CE288F8367e1Bb143E90bb3F0512"
                },
                "WegaChanceGame": {
                    "address": "0xDc64a140Aa3E981100a9becA4E685f962f0cF6C9",
                    "legacyAddresses": [],
                    "deploymentBlock": "0x05",
                    "implementation": "0xCf7Ed3AccA5a467e9e704C703E8D87F634fB0Fc9"
                }
            }
        },
        "80001": {
            "contracts": {
                "WegaERC20Escrow": {
                    "address": "0x08052EEaf0c3F42cd38331E1C3D188Cd108E0C10",
                    "legacyAddresses": [],
                    "deploymentBlock": "0x0263113a",
                    "implementation": "0xf731b996738AA8909Ca18f8954395Ff4b62B305d"
                },
                "WegaERC20Dummy": {
                    "address": "0x818120D7f6C1f96C3ddb45B1363752E6688F3a9C",
                    "legacyAddresses": [],
                    "deploymentBlock": "0x0263112e"
                },
                "WegaGameController": {
                    "address": "0xC69cD908504C554eaD8D24354e018e3a37e7F29b",
                    "legacyAddresses": [
                        "0x760D87Ce891F301d19F608044D42356De2D50D14",
                        "0x740e1416aE865E2bff8f95aa5776F5Fa0a3706e7",
                        "0x02D7EF0f678BCd9323f2FA88e7197528D113f24a",
                        "0x0000000000000000000000000000000000000000"
                    ],
                    "deploymentBlock": "0x0272c37b",
                    "implementation": "0xAF0A650F026419776015fF248DFefC2768497C4C"
                },
                "WegaRandomNumberController": {
                    "address": "0xaBC8837A5756aF9a915a8cC77b80b06c1997e17e",
                    "legacyAddresses": [],
                    "deploymentBlock": "0x02631148",
                    "implementation": "0xCC6e334201974DF201EBb4bd84b97ac232fE7380"
                },
                "WegaDiceGame": {
                    "address": "0x95c44B6F23D361c071667129F2A06Ae4275d7cC6",
                    "legacyAddresses": [],
                    "deploymentBlock": "0x0263116f",
                    "implementation": "0x18279b8235b84f68db39f76aF481DcD5aBa75218"
                },
                "WegaCoinFlipGame": {
                    "address": "0x80B0AC09f6c42c0010731186DCBfbeb9D1A1C76f",
                    "legacyAddresses": [],
                    "deploymentBlock": "0x02631158",
                    "implementation": "0x1d4A2C0Ce54525f555Bbe772f5b8132ECf2002BD"
                },
                "FeeManager": {
                    "address": "0x0000000000000000000000000000000000000000"
                }
            }
        },
        "344106930": {
            "contracts": {
                "WegaERC20Escrow": {
                    "address": "0x0000000000000000000000000000000000000000"
                },
                "WegaERC20Dummy": {
                    "address": "0x0000000000000000000000000000000000000000"
                },
                "WegaGameController": {
                    "address": "0x0000000000000000000000000000000000000000"
                },
                "WegaRandomNumberController": {
                    "address": "0x0000000000000000000000000000000000000000"
                },
                "WegaDiceGame": {
                    "address": "0x0000000000000000000000000000000000000000"
                },
                "WegaCoinFlipGame": {
                    "address": "0x0000000000000000000000000000000000000000"
                },
                "FeeManager": {
                    "address": "0x0000000000000000000000000000000000000000"
                }
            }
        }
    }
}
